zeplyn/__init__.py
zeplyn/zeplyn.py
zeplyn-0.1.1.dist-info/entry_points.txt
zeplyn-0.1.1.dist-info/WHEEL
zeplyn-0.1.1.dist-info/METADATA
zeplyn-0.1.1.dist-info/RECORD
