Metadata-Version: 2.1
Name: zeplyn
Version: 0.1.1
Summary: Zeplyn allows to you release python package fastly and easily in one command
Author: ssantoshp
Author-email: santoshpassoubady@gmail.com
Requires-Python: >=3.9,<4.0
Classifier: Programming Language :: Python :: 3
Classifier: Programming Language :: Python :: 3.9
Requires-Dist: twine (==3.4.1)
Requires-Dist: typer[all] (>=0.3.2,<0.4.0)
